qrawl/__init__.py
qrawl/common.py
qrawl/exceptions.py
qrawl/google_sheets/__init__.py
qrawl/google_sheets/column.py
qrawl/playwright/async_api/__init__.py
qrawl/playwright/async_api/async_playwright.py
qrawl/playwright/async_api/common.py
qrawl/playwright/sync_api/__init__.py
qrawl/playwright/sync_api/common.py
qrawl/playwright/sync_api/sync_playwright.py
qrawl/scrapy/__init__.py
qrawl/selenium/__init__.py
qrawl/selenium/browsermob_proxy_wrapper.py
qrawl/selenium/exceptions.py
qrawl/selenium/locator.py
qrawl/selenium/selenium.py
qrawl/xpath.py
qrawl-0.2.15.dist-info/LICENSE
qrawl-0.2.15.dist-info/METADATA
qrawl-0.2.15.dist-info/WHEEL
qrawl-0.2.15.dist-info/RECORD
