Metadata-Version: 2.1
Name: qrawl
Version: 0.2.15
Summary: Python Crawling Utilities.
License: Apache 2.0
Author: GGLionCross
Requires-Python: >=3.10,<4.0
Classifier: License :: Other/Proprietary License
Classifier: Programming Language :: Python :: 3
Classifier: Programming Language :: Python :: 3.10
Classifier: Programming Language :: Python :: 3.11
Classifier: Programming Language :: Python :: 3.12
